gfetch/__init__.py
gfetch/app.py
gfetch/auth.py
gfetch/credentials.json
gfetch/emails.py
gfetch/scratch.py
gfetch/token.json
gfetch-0.1.6.dist-info/WHEEL
gfetch-0.1.6.dist-info/entry_points.txt
gfetch-0.1.6.dist-info/METADATA
gfetch-0.1.6.dist-info/RECORD
