Metadata-Version: 2.3
Name: gfetch
Version: 0.1.6
Summary: A CLI app to back up your gmail emails locally
Author: Jeff Jacobson
Author-email: Jeff Jacobson <jeffjacobsonhimself@gmail.com>
License:                     GNU GENERAL PUBLIC LICENSE
Classifier: Development Status :: 3 - Alpha
Classifier: Environment :: Console
Classifier: Intended Audience :: End Users/Desktop
Classifier: License :: OSI Approved :: GNU General Public License v3 (GPLv3)
Classifier: Natural Language :: English
Classifier: Operating System :: OS Independent
Classifier: Programming Language :: Python
Classifier: Programming Language :: Python :: 3
Classifier: Programming Language :: Python :: 3 :: Only
Classifier: Programming Language :: Python :: 3.13
Classifier: Topic :: Communications :: Email
Classifier: Topic :: Internet
Classifier: Topic :: System :: Archiving :: Backup
Classifier: Topic :: Text Processing
Requires-Dist: google-api-python-client>=2.176.0
Requires-Dist: google-auth>=2.40.3
Requires-Dist: google-auth-httplib2>=0.2.0
Requires-Dist: google-auth-oauthlib>=1.2.2
Requires-Dist: python-decouple>=3.8
Requires-Python: >=3.13
Project-URL: Homepage, https://github.com/jwjacobson/gfetch-cli
Project-URL: Issues, https://github.com/jwjacobson/gfetch-cli/issues
